lfa_toolbox/__init__.py
lfa_toolbox/core/__init__.py
lfa_toolbox/core/fis/__init__.py
lfa_toolbox/core/fis/fis.py
lfa_toolbox/core/fis/singleton_fis.py
lfa_toolbox/core/labels/__init__.py
lfa_toolbox/core/labels/fuzzy_labels_generator.py
lfa_toolbox/core/lv/__init__.py
lfa_toolbox/core/lv/linguistic_variable.py
lfa_toolbox/core/lv/p_points_lv.py
lfa_toolbox/core/lv/three_points_lv.py
lfa_toolbox/core/mf/__init__.py
lfa_toolbox/core/mf/free_shape_mf.py
lfa_toolbox/core/mf/gaussian_mf.py
lfa_toolbox/core/mf/lin_piece_wise_mf.py
lfa_toolbox/core/mf/singleton_mf.py
lfa_toolbox/core/mf/trap_mf.py
lfa_toolbox/core/mf/triangular_mf.py
lfa_toolbox/core/rules/__init__.py
lfa_toolbox/core/rules/default_fuzzy_rule.py
lfa_toolbox/core/rules/fuzzy_rule.py
lfa_toolbox/core/rules/fuzzy_rule_element.py
lfa_toolbox/examples/__init__.py
lfa_toolbox/examples/car_acceleration.py
lfa_toolbox/examples/exam_problem.py
lfa_toolbox/examples/hotel_problem.py
lfa_toolbox/examples/hotel_problem_student.py
lfa_toolbox/examples/import_a_trefle_fuzzy_system.py
lfa_toolbox/examples/octave_tip_problem.py
lfa_toolbox/examples/readme_examples.py
lfa_toolbox/examples/resort_problem.py
lfa_toolbox/examples/tip_problem.py
lfa_toolbox/examples/car_problem_slides/__init__.py
lfa_toolbox/examples/car_problem_slides/car_problem_all.py
lfa_toolbox/examples/car_problem_slides/car_problem_default_rule.py
lfa_toolbox/examples/car_problem_slides/car_problem_default_rule_and_not.py
lfa_toolbox/examples/car_problem_slides/car_problem_mamdani.py
lfa_toolbox/examples/car_problem_slides/car_problem_singleton.py
lfa_toolbox/examples/iris/__init__.py
lfa_toolbox/examples/iris/iris_classifier_type.py
lfa_toolbox/examples/iris/iris_controller_type.py
lfa_toolbox/trefle/__init__.py
lfa_toolbox/trefle/tff_json_to_singletonfis.py
lfa_toolbox/trefle/tffconverter.py
lfa_toolbox/view/__init__.py
lfa_toolbox/view/fis_surface.py
lfa_toolbox/view/fis_viewer.py
lfa_toolbox/view/lv_viewer.py
lfa_toolbox/view/mf_viewer.py
lfa_toolbox-0.2.dist-info/LICENSE
lfa_toolbox-0.2.dist-info/METADATA
lfa_toolbox-0.2.dist-info/WHEEL
lfa_toolbox-0.2.dist-info/top_level.txt
lfa_toolbox-0.2.dist-info/RECORD
