Metadata-Version: 2.1
Name: lfa-toolbox
Version: 0.2
Summary: LFA Toolbox is an educational library to play with fuzzy systems
Home-page: http://iict-space.heig-vd.ch/cpn/
Author: Gary Marigliano
Author-email: UNKNOWN
License: GPL
Platform: UNKNOWN
Requires-Python: >=3.5
Requires-Dist: numpy (>=1.10)
Requires-Dist: matplotlib (>=2.1.1)
